data_file.py
state_lookup.py
state_lookup-0.2.2.data/data/city_state_map.txt
state_lookup-0.2.2.dist-info/METADATA
state_lookup-0.2.2.dist-info/WHEEL
state_lookup-0.2.2.dist-info/top_level.txt
state_lookup-0.2.2.dist-info/RECORD
