Metadata-Version: 2.1
Name: state-lookup
Version: 0.2.2
Summary: Find the state in which the city is
Home-page: UNKNOWN
Author: Deepak Sharma
License: UNKNOWN
Platform: UNKNOWN
Classifier: Programming Language :: Python :: 3
Classifier: License :: OSI Approved :: MIT License
Classifier: Operating System :: OS Independent
Requires-Python: >=3.6
